polhemus/FTCmdIF.dll
polhemus/FTCmdIFD.dll
polhemus/FTCmdIFU.dll
polhemus/FTCmdIFUD.dll
polhemus/G4CmdIF.dll
polhemus/G4CmdIFD.dll
polhemus/G4CmdIFU.dll
polhemus/G4CmdIFUD.dll
polhemus/G4Track.dll
polhemus/G4TrackD.dll
polhemus/PDI.dll
polhemus/PDID.dll
polhemus/PDIU.dll
polhemus/PDIUD.dll
polhemus/PiCmdIF.dll
polhemus/PiCmdIFD.dll
polhemus/PiCmdIFU.dll
polhemus/PiCmdIFUD.dll
polhemus/__init__.py
polhemus/_polhemus.pyd
polhemus-0.0.3.dist-info/LICENSE
polhemus-0.0.3.dist-info/METADATA
polhemus-0.0.3.dist-info/WHEEL
polhemus-0.0.3.dist-info/top_level.txt
polhemus-0.0.3.dist-info/RECORD
