Metadata-Version: 2.1
Name: polhemus
Version: 0.0.3
Summary: polhemus c++ wrapper for python 38
Home-page: UNKNOWN
Author: Renan Matsuda
Author-email: renan_hiroshi@hotmail.com
License: UNKNOWN
Platform: UNKNOWN
Classifier: Programming Language :: Python :: 3
Classifier: License :: OSI Approved :: MIT License
Classifier: Operating System :: Microsoft :: Windows
